symmetria/__init__.py
symmetria/__main__.py
symmetria/cli/__init__.py
symmetria/cli/_commands.py
symmetria/cli/cli.py
symmetria/elements/__init__.py
symmetria/elements/_base.py
symmetria/elements/_types.py
symmetria/elements/cycle.py
symmetria/elements/cycle_decomposition.py
symmetria/elements/permutation.py
symmetria/generators/__init__.py
symmetria/generators/_validators.py
symmetria/generators/algorithm/__init__.py
symmetria/generators/algorithm/_algorithms.py
symmetria/generators/algorithm/api.py
symmetria/generators/random/__init__.py
symmetria/generators/random/_algorithms.py
symmetria/generators/random/api.py
symmetria/groups/__init__.py
symmetria/groups/symmetric.py
symmetria-1.0.0.dist-info/licenses/LICENSE.txt
symmetria-1.0.0.dist-info/METADATA
symmetria-1.0.0.dist-info/WHEEL
symmetria-1.0.0.dist-info/entry_points.txt
symmetria-1.0.0.dist-info/top_level.txt
symmetria-1.0.0.dist-info/RECORD
